MANIFEST.in
README.rst
requirements.pip
setup.py
device_proxy.egg-info/PKG-INFO
device_proxy.egg-info/SOURCES.txt
device_proxy.egg-info/dependency_links.txt
device_proxy.egg-info/requires.txt
device_proxy.egg-info/top_level.txt
devproxy/__init__.py
devproxy/proxy.py
devproxy/handlers/__init__.py
devproxy/handlers/base.py
devproxy/handlers/demo.py
devproxy/handlers/wurfl_handler/__init__.py
devproxy/handlers/wurfl_handler/base.py
devproxy/handlers/wurfl_handler/debug.py
devproxy/handlers/wurfl_handler/scientia_mobile_cloud.py
devproxy/handlers/wurfl_handler/scientia_mobile_cloud_resolution.py
devproxy/handlers/wurfl_handler/simple.py
devproxy/handlers/wurfl_handler/wurfl_devices.py
devproxy/tests/__init__.py
devproxy/tests/test_demo.py
devproxy/tests/test_proxy.py
devproxy/tests/test_wurfl_handler.py
devproxy/tests/test_wurfl_scientia_mobile_cloud.py
devproxy/tests/utils.py
devproxy/utils/__init__.py
devproxy/utils/http.py
devproxy/utils/memcached.py
twisted/plugins/devproxy_plugin.py
twisted/plugins/devproxy_plugin.pyc
twisted/plugins/dropin.cache