Metadata-Version: 1.1
Name: device-proxy
Version: 0.4.1
Summary: Device Proxy. A reverse HTTP Proxy that can inspect and manipulate HTTP Headers before sending upstream.
Home-page: http://github.com/praekelt/device-proxy
Author: Praekelt Foundation
Author-email: dev@praekeltfoundation.org
License: BSD
Platform: UNKNOWN
Classifier: Development Status :: 4 - Beta
Classifier: Intended Audience :: Developers
Classifier: License :: OSI Approved :: BSD License
Classifier: Operating System :: POSIX
Classifier: Programming Language :: Python
Classifier: Topic :: Software Development :: Libraries :: Python Modules
Classifier: Topic :: System :: Networking
